src/design/bin_to_bcd.sv
// bin_to_bcd.sv
// Conversor de número binario a representación BCD usando el algoritmo

module bin_to_bcd #(
    parameter int BIN_W    = 6,
    parameter int N_DIGITS = 2
)(
    input  logic [BIN_W-1:0]      bin_in,
    output logic [N_DIGITS*4-1:0] bcd_out
);

    localparam int TOTAL_W = N_DIGITS * 4 + BIN_W;

    logic [TOTAL_W-1:0] scratch;

    always_comb begin
        scratch = {{(N_DIGITS*4){1'b0}}, bin_in};

        for (int i = 0; i < BIN_W; i++) begin

            for (int j = 0; j < N_DIGITS; j++) begin
                if (scratch[BIN_W + j*4 +: 4] >= 4'd5)
                    scratch[BIN_W + j*4 +: 4] =
                        scratch[BIN_W + j*4 +: 4] + 4'd3;
            end

            scratch = {scratch[TOTAL_W-2:0], 1'b0};
        end

        bcd_out = scratch[TOTAL_W-1 : BIN_W];
    end

endmodule

src/sim/tb_bin_to_bcd.sv
`timescale 1ns/1ps

// tb_bin_to_bcd.sv - Módulo tb_bin_to_bcd

module tb_bin_to_bcd;

    localparam BIN_W    = 6;
    localparam N_DIGITS = 2;

    logic [BIN_W-1:0] bin_in;
    logic [N_DIGITS*4-1:0] bcd_out;

    bin_to_bcd #(
        .BIN_W(BIN_W),
        .N_DIGITS(N_DIGITS)
    ) dut (
        .bin_in(bin_in),
        .bcd_out(bcd_out)
    );

    initial begin

        $dumpfile("bin_to_bcd.vcd");
        $dumpvars(0, tb_bin_to_bcd);

        bin_in = 0;
        #10;

        bin_in = 1;
        #10;

        bin_in = 9;
        #10;

        bin_in = 10;
        #10;

        bin_in = 15;
        #10;

        bin_in = 31;
        #10;

        bin_in = 45;
        #10;

        bin_in = 63;
        #10;

        $finish;

    end

endmodule

src/build/bin_to_bcd.vcd
$date
	Tue Jun 09 21:04:24 2026
$end
$version
	Icarus Verilog
$end
$timescale
	1ps
$end
$scope module tb_bin_to_bcd $end
$var wire 8 ! bcd_out [7:0] $end
$var parameter 32 " BIN_W $end
$var parameter 32 # N_DIGITS $end
$var reg 6 $ bin_in [5:0] $end
$scope module dut $end
$var wire 6 % bin_in [5:0] $end
$var parameter 32 & BIN_W $end
$var parameter 32 ' N_DIGITS $end
$var parameter 32 ( TOTAL_W $end
$var reg 8 ) bcd_out [7:0] $end
$var reg 14 * scratch [13:0] $end
$scope begin $ivl_for_loop0 $end
$var integer 32 + i [31:0] $end
$scope begin $ivl_for_loop1 $end
$var integer 32 , j [31:0] $end
$upscope $end
$upscope $end
$upscope $end
$upscope $end
$enddefinitions $end
$comment Show the parameter values. $end
$dumpall
b1110 (
b10 '
b110 &
b10 #
b110 "
$end
#0
$dumpvars
b10 ,
b110 +
b0 *
b0 )
b0 %
b0 $
b0 !
$end
#10000
b1 !
b1 )
b10 ,
b110 +
b1000000 *
b1 $
b1 %
#20000
b1001 !
b1001 )
b10 ,
b110 +
b1001000000 *
b1001 $
b1001 %
#30000
b10000 !
b10000 )
b10 ,
b110 +
b10000000000 *
b1010 $
b1010 %
#40000
b10101 !
b10101 )
b10 ,
b110 +
b10101000000 *
b1111 $
b1111 %
#50000
b110001 !
b110001 )
b10 ,
b110 +
b110001000000 *
b11111 $
b11111 %
#60000
b1000101 !
b1000101 )
b10 ,
b110 +
b1000101000000 *
b101101 $
b101101 %
#70000
b1100011 !
b1100011 )
b10 ,
b110 +
b1100011000000 *
b111111 $
b111111 %
