src/design/bin_to_bcd.sv
// bin_to_bcd.sv
// Conversor de número binario a representación BCD usando el algoritmo
// "Double Dabble" (shift-and-add-3). Totalmente combinacional.
//
// Algoritmo (BIN_W iteraciones):
//   1. Verificar cada dígito BCD: si el dígito >= 5, sumar 3.
//   2. Desplazar todo el registro (BCD + binario) un lugar a la izquierda.
//
// Parámetros:
//   BIN_W    = ancho del número binario de entrada
//   N_DIGITS = cantidad de dígitos BCD de salida (cada uno es 4 bits)
//
// Uso en el proyecto:
//   • Cociente (0..63):  bin_to_bcd #(.BIN_W(6), .N_DIGITS(2)) u_bcd_q (...)
//   • Residuo  (0..14):  bin_to_bcd #(.BIN_W(4), .N_DIGITS(2)) u_bcd_r (...)
//
// Ejemplo (BIN_W=6, N_DIGITS=2):
//   bin_in  = 6'd63  → bcd_out = 8'h63 (tens=6, units=3)
//   bin_in  = 6'd14  → bcd_out = 8'h14 (tens=1, units=4)
//
// bcd_out[N_DIGITS*4-1 : (N_DIGITS-1)*4] = dígito más significativo (decenas)
// bcd_out[3:0]                            = dígito menos significativo (unidades)

module bin_to_bcd #(
    parameter int BIN_W    = 6,   // bits del número binario de entrada
    parameter int N_DIGITS = 2    // dígitos BCD de salida
)(
    input  logic [BIN_W-1:0]      bin_in,
    output logic [N_DIGITS*4-1:0] bcd_out
);

    localparam int TOTAL_W = N_DIGITS * 4 + BIN_W; // ancho del registro de trabajo

    // Registro de trabajo: [BCD_N-1 ... BCD_0 | bin_in]
    logic [TOTAL_W-1:0] scratch;

    always_comb begin
        // Inicializar: dígitos BCD en 0, binario en los LSBs
        scratch = {{(N_DIGITS*4){1'b0}}, bin_in};

        // BIN_W iteraciones: verificar → sumar 3 si >= 5 → desplazar
        for (int i = 0; i < BIN_W; i++) begin

            // Verificar y ajustar cada dígito BCD (de unidades hacia arriba)
            for (int j = 0; j < N_DIGITS; j++) begin
                if (scratch[BIN_W + j*4 +: 4] >= 4'd5)
                    scratch[BIN_W + j*4 +: 4] =
                        scratch[BIN_W + j*4 +: 4] + 4'd3;
            end

            // Desplazamiento izquierda: el MSB del binario sube a BCD_units
            scratch = {scratch[TOTAL_W-2:0], 1'b0};
        end

        // Los dígitos BCD quedaron en los bits superiores del registro
        bcd_out = scratch[TOTAL_W-1 : BIN_W];
    end

endmodule

src/sim/tb_bin_to_bcd.sv
`timescale 1ns/1ps

module tb_bin_to_bcd;

    localparam BIN_W    = 6;
    localparam N_DIGITS = 2;

    logic [BIN_W-1:0] bin_in;
    logic [N_DIGITS*4-1:0] bcd_out;

    // DUT
    bin_to_bcd #(
        .BIN_W(BIN_W),
        .N_DIGITS(N_DIGITS)
    ) dut (
        .bin_in(bin_in),
        .bcd_out(bcd_out)
    );

    initial begin

        // Crear archivo de ondas
        $dumpfile("bin_to_bcd.vcd");
        $dumpvars(0, tb_bin_to_bcd);

        // Caso 0
        bin_in = 0;
        #10;

        // Caso 1
        bin_in = 1;
        #10;

        // Caso 9
        bin_in = 9;
        #10;

        // Caso 10
        bin_in = 10;
        #10;

        // Caso 15
        bin_in = 15;
        #10;

        // Caso 31
        bin_in = 31;
        #10;

        // Caso 45
        bin_in = 45;
        #10;

        // Máximo valor para 6 bits
        bin_in = 63;
        #10;

        $finish;

    end

endmodule

src/build/bin_to_bcd.vcd
$date
	Sat Jun 06 19:33:49 2026
$end
$version
	Icarus Verilog
$end
$timescale
	1ps
$end
$scope module tb_bin_to_bcd $end
$var wire 8 ! bcd_out [7:0] $end
$var parameter 32 " BIN_W $end
$var parameter 32 # N_DIGITS $end
$var reg 6 $ bin_in [5:0] $end
$scope module dut $end
$var wire 6 % bin_in [5:0] $end
$var parameter 32 & BIN_W $end
$var parameter 32 ' N_DIGITS $end
$var parameter 32 ( TOTAL_W $end
$var reg 8 ) bcd_out [7:0] $end
$var reg 14 * scratch [13:0] $end
$scope begin $ivl_for_loop0 $end
$var integer 32 + i [31:0] $end
$scope begin $ivl_for_loop1 $end
$var integer 32 , j [31:0] $end
$upscope $end
$upscope $end
$upscope $end
$upscope $end
$enddefinitions $end
$comment Show the parameter values. $end
$dumpall
b1110 (
b10 '
b110 &
b10 #
b110 "
$end
#0
$dumpvars
b10 ,
b110 +
b0 *
b0 )
b0 %
b0 $
b0 !
$end
#10000
b1 !
b1 )
b10 ,
b110 +
b1000000 *
b1 $
b1 %
#20000
b1001 !
b1001 )
b10 ,
b110 +
b1001000000 *
b1001 $
b1001 %
#30000
b10000 !
b10000 )
b10 ,
b110 +
b10000000000 *
b1010 $
b1010 %
#40000
b10101 !
b10101 )
b10 ,
b110 +
b10101000000 *
b1111 $
b1111 %
#50000
b110001 !
b110001 )
b10 ,
b110 +
b110001000000 *
b11111 $
b11111 %
#60000
b1000101 !
b1000101 )
b10 ,
b110 +
b1000101000000 *
b101101 $
b101101 %
#70000
b1100011 !
b1100011 )
b10 ,
b110 +
b1100011000000 *
b111111 $
b111111 %
