src/design/division_unit.sv
// ============================================================
// ESTRUCTURA (Figura 2 del enunciado, Harris & Harris §5.2.7)
//
//  valid ──► [Reg entrada: A, B]
//                  │
//            [Fila 0 – 5 FA combinacional]
//                  │
//            ══[REG pipeline 0]══          ← registro entre fila 0 y 1
//                  │
//            [Fila 1 – 5 FA combinacional]
//                  │
//            ══[REG pipeline 1]══          ← registro entre fila 1 y 2
//                  │
//                 ...
//                  │
//            [Fila 5 – 5 FA combinacional]
//                  │
//            ══[REG pipeline 5]══   ──► done, Q, R
//
// Latencia    : NA = 6 ciclos de reloj
// Ruta crítica: NB+1 = 5 full adders (una sola fila)
// Frecuencia  : 27 MHz  ✓
//
// Por qué esto es distinto a la FSM (versión anterior):
//   - FSM       : 1 fila reutilizada en 6 ciclos (un solo conjunto de FAs)
//   - Pipeline  : 6 filas físicas distintas, una por ciclo, con FF entre ellas
//   - Ambas dan la misma latencia (6 ciclos) y frecuencia, pero el pipeline
//     muestra la segmentación explícita que describe el enunciado.
//
// Señales de pipeline (índice k = 0..NA):
//   r_p[k]  : residuo parcial de NB bits   — salida de la fila k-1
//   q_p[k]  : cociente acumulado de NA bits — salida de la fila k-1
//   a_p[k]  : dividendo desplazado          — MSB = bit a procesar en fila k
//   b_p[k]  : divisor propagado             — reduce ruta crítica al evitar
//              fanout desde la entrada original hasta cada fila
//   v_p[k]  : bandera valid                 — fluye junto con los datos
// ============================================================

module division_unit #(
    parameter int NA = 6,   // bits del dividendo  (máx: 2^NA−1 = 63)
    parameter int NB = 4    // bits del divisor    (máx: 2^NB−1 = 15)
)(
    input  logic          clk,
    input  logic          rst_n,   // reset activo-bajo
    input  logic          valid,   // pulso 1 ciclo: inicia la división
    input  logic [NA-1:0] A,       // dividendo
    input  logic [NB-1:0] B,       // divisor
    output logic [NA-1:0] Q,       // cociente  (estable cuando done = 1)
    output logic [NB-1:0] R,       // residuo   (estable cuando done = 1)
    output logic          done     // pulso 1 ciclo: resultado listo
);

    // ── Registros de pipeline ────────────────────────────────────────
    // r_p, q_p : rango [1:NA]  → escritos por las filas 0..NA-1
    // a_p, b_p : rango [0:NA]  → a_p[0]/b_p[0] = registro de entrada
    // v_p      : rango [0:NA]  → v_p[0] = registro de entrada, v_p[NA] = done
    logic [NB-1:0] r_p [1:NA];
    logic [NA-1:0] q_p [1:NA];
    logic [NA-1:0] a_p [0:NA];
    logic [NB-1:0] b_p [0:NA];
    logic          v_p [0:NA];

    // ── Registro de entrada ──────────────────────────────────────────
    // Captura A y B en el ciclo en que valid = 1.
    // v_p[0] propaga la bandera "dato válido" a través del pipeline.
    always_ff @(posedge clk or negedge rst_n) begin
        if (!rst_n) begin
            a_p[0] <= '0;
            b_p[0] <= '0;
            v_p[0] <= 1'b0;
        end else begin
            v_p[0] <= valid;
            if (valid) begin
                a_p[0] <= A;
                b_p[0] <= B;
            end
        end
    end

    // ── NA etapas de pipeline ────────────────────────────────────────
    // Cada etapa implementa UNA fila del arreglo de la Figura 2:
    //   1. Computa r_ext = {residuo_previo, bit_dividendo}  (NB+1 bits)
    //   2. Calcula D = r_ext - B via complemento a dos      (NB+2 bits)
    //   3. Determina Q_bit = carry_out (1 → D≥0, 0 → D<0)
    //   4. Registra el nuevo residuo, cociente y contexto
    genvar k;
    generate
        for (k = 0; k < NA; k++) begin : gen_fila

            // ── Señales de entrada de esta etapa ──────────────────────
            // r_prev y q_prev son los valores que entran a esta fila:
            //   • Fila 0 (k=0): residuo y cociente iniciales = 0
            //   • Filas 1..NA-1: provenientes del registro de pipeline k
            // Usar generate-if garantiza que el índice nunca esté fuera de rango.
            logic [NB-1:0] r_prev;
            logic [NA-1:0] q_prev;

            if (k == 0) begin : g_entrada_primera
                assign r_prev = {NB{1'b0}};   // Fila 0: residuo inicial = 0
                assign q_prev = {NA{1'b0}};   // Fila 0: cociente inicial = 0
            end else begin : g_entrada_resto
                assign r_prev = r_p[k];        // Desde el REG de la fila anterior
                assign q_prev = q_p[k];
            end

            // ── Cómputo combinacional de la fila k ────────────────────
            // r_ext = {residuo_previo[NB-1:0], bit_k_del_dividendo}
            // El MSB de a_p[k] es siempre el próximo bit a procesar
            // (se va desplazando izquierda en cada etapa).
            logic [NB:0]   r_ext;   // residuo extendido (NB+1 bits)
            logic [NB+1:0] sub;     // resultado de la resta (NB+2 bits)
            logic          q_bit;   // bit del cociente de esta fila

            assign r_ext = {r_prev, a_p[k][NA-1]};

            // D = r_ext − B  →  r_ext + ~{0,B} + 1  (complemento a dos)
            // sub[NB+1] = carry_out:
            //   1 → D ≥ 0 → Q_bit = 1, nuevo residuo = D[NB-1:0]
            //   0 → D < 0 → Q_bit = 0, nuevo residuo = r_ext[NB-1:0]
            assign sub   = {1'b0, r_ext}
                         + {1'b0, {1'b1, ~b_p[k]}}
                         + {{(NB+1){1'b0}}, 1'b1};
            assign q_bit = sub[NB+1];

            // ── Registro de pipeline entre fila k y fila k+1 ─────────
            // Este es el "REG" que se muestra en el diagrama de bloques.
            // Captura en el flanco de reloj y presenta los datos a la
            // siguiente fila combinacional en el ciclo siguiente.
            always_ff @(posedge clk or negedge rst_n) begin
                if (!rst_n) begin
                    r_p[k+1] <= '0;
                    q_p[k+1] <= '0;
                    a_p[k+1] <= '0;
                    b_p[k+1] <= '0;
                    v_p[k+1] <= 1'b0;
                end else begin
                    // Nuevo residuo parcial
                    r_p[k+1] <= q_bit ? sub[NB-1:0] : r_ext[NB-1:0];

                    // Cociente acumulado: desplazamiento izquierda, q_bit en LSB.
                    // q_prev[NA-2:0] = bits previos; q_bit = bit de esta fila.
                    // Para k=0: q_prev = 0 → q_p[1] = {5'b0, q_bit}
                    // Para k=5: q_p[6] = {Q[5],Q[4],...,Q[0]} = cociente final
                    q_p[k+1] <= {q_prev[NA-2:0], q_bit};

                    // Dividendo desplazado para la siguiente fila:
                    // el bit ya procesado sale por MSB, un 0 entra por LSB.
                    a_p[k+1] <= {a_p[k][NA-2:0], 1'b0};

                    // Divisor y bandera valid se propagan sin modificación
                    b_p[k+1] <= b_p[k];
                    v_p[k+1] <= v_p[k];
                end
            end

        end
    endgenerate

    // ── Salidas ───────────────────────────────────────────────────────
    // Después de NA ciclos desde valid=1, los datos llegan a la etapa final.
    // done = v_p[NA] es un pulso de 1 ciclo de ancho.
    // Q y R son válidos mientras done permanezca alto (1 ciclo) y no cambian
    // hasta que comience la siguiente operación.
    assign Q    = q_p[NA];
    assign R    = r_p[NA];
    assign done = v_p[NA];

endmodule

src/sim/tb_division_unit.sv
`timescale 1ns/1ps

module tb_division_unit;

    localparam NA = 6;
    localparam NB = 4;

    logic clk;
    logic rst_n;
    logic valid;

    logic [NA-1:0] A;
    logic [NB-1:0] B;

    logic [NA-1:0] Q;
    logic [NB-1:0] R;
    logic done;

    division_unit #(
        .NA(NA),
        .NB(NB)
    ) dut (
        .clk(clk),
        .rst_n(rst_n),
        .valid(valid),
        .A(A),
        .B(B),
        .Q(Q),
        .R(R),
        .done(done)
    );

    // 27 MHz
    always #18.518 clk = ~clk;

    initial begin

        $dumpfile("tb_division_unit.vcd");
        $dumpvars(0, tb_division_unit);

        clk   = 0;
        rst_n = 0;
        valid = 0;
        A     = 0;
        B     = 0;

        // reset
        #100;
        rst_n = 1;

        // 12 / 3
        @(posedge clk);
        A = 12;
        B = 3;
        valid = 1;

        @(posedge clk);
        valid = 0;

        // esperar salida
        repeat(10) @(posedge clk);

        // 15 / 4
        A = 15;
        B = 4;
        valid = 1;

        @(posedge clk);
        valid = 0;

        repeat(10) @(posedge clk);

        $finish;

    end

endmodule

src/build/tb_division_unit.vcd
$date
	Sat Jun 06 21:24:46 2026
$end
$version
	Icarus Verilog
$end
$timescale
	1ps
$end
$scope module tb_division_unit $end
$var wire 1 ! done $end
$var wire 4 " R [3:0] $end
$var wire 6 # Q [5:0] $end
$var parameter 32 $ NA $end
$var parameter 32 % NB $end
$var reg 6 & A [5:0] $end
$var reg 4 ' B [3:0] $end
$var reg 1 ( clk $end
$var reg 1 ) rst_n $end
$var reg 1 * valid $end
$scope module dut $end
$var wire 6 + A [5:0] $end
$var wire 4 , B [3:0] $end
$var wire 6 - Q [5:0] $end
$var wire 4 . R [3:0] $end
$var wire 1 ( clk $end
$var wire 1 ! done $end
$var wire 1 ) rst_n $end
$var wire 1 * valid $end
$var parameter 32 / NA $end
$var parameter 32 0 NB $end
$scope begin gen_fila[0] $end
$var wire 6 1 q_prev [5:0] $end
$var wire 4 2 r_prev [3:0] $end
$var wire 6 3 sub [5:0] $end
$var wire 5 4 r_ext [4:0] $end
$var wire 1 5 q_bit $end
$var parameter 2 6 k $end
$scope begin g_entrada_primera $end
$upscope $end
$upscope $end
$scope begin gen_fila[1] $end
$var wire 4 7 r_prev [3:0] $end
$var wire 6 8 sub [5:0] $end
$var wire 5 9 r_ext [4:0] $end
$var wire 6 : q_prev [5:0] $end
$var wire 1 ; q_bit $end
$var parameter 2 < k $end
$scope begin g_entrada_resto $end
$upscope $end
$upscope $end
$scope begin gen_fila[2] $end
$var wire 4 = r_prev [3:0] $end
$var wire 6 > sub [5:0] $end
$var wire 5 ? r_ext [4:0] $end
$var wire 6 @ q_prev [5:0] $end
$var wire 1 A q_bit $end
$var parameter 3 B k $end
$scope begin g_entrada_resto $end
$upscope $end
$upscope $end
$scope begin gen_fila[3] $end
$var wire 4 C r_prev [3:0] $end
$var wire 6 D sub [5:0] $end
$var wire 5 E r_ext [4:0] $end
$var wire 6 F q_prev [5:0] $end
$var wire 1 G q_bit $end
$var parameter 3 H k $end
$scope begin g_entrada_resto $end
$upscope $end
$upscope $end
$scope begin gen_fila[4] $end
$var wire 4 I r_prev [3:0] $end
$var wire 6 J sub [5:0] $end
$var wire 5 K r_ext [4:0] $end
$var wire 6 L q_prev [5:0] $end
$var wire 1 M q_bit $end
$var parameter 4 N k $end
$scope begin g_entrada_resto $end
$upscope $end
$upscope $end
$scope begin gen_fila[5] $end
$var wire 4 O r_prev [3:0] $end
$var wire 6 P sub [5:0] $end
$var wire 5 Q r_ext [4:0] $end
$var wire 6 R q_prev [5:0] $end
$var wire 1 S q_bit $end
$var parameter 4 T k $end
$scope begin g_entrada_resto $end
$upscope $end
$upscope $end
$upscope $end
$upscope $end
$enddefinitions $end
$comment Show the parameter values. $end
$dumpall
b101 T
b100 N
b11 H
b10 B
b1 <
b0 6
b100 0
b110 /
b100 %
b110 $
$end
#0
$dumpvars
1S
b0 R
b0 Q
b100000 P
b0 O
1M
b0 L
b0 K
b100000 J
b0 I
1G
b0 F
b0 E
b100000 D
b0 C
1A
b0 @
b0 ?
b100000 >
b0 =
1;
b0 :
b0 9
b100000 8
b0 7
15
b0 4
b100000 3
b0 2
b0 1
b0 .
b0 -
b0 ,
b0 +
0*
0)
0(
b0 '
b0 &
b0 #
b0 "
0!
$end
#18518
1(
#37036
0(
#55554
1(
#74072
0(
#92590
1(
#100000
1)
#111108
0(
#129626
05
b11101 3
b1 :
b1 @
b1 F
b1 L
b1 R
b1 #
b1 -
1*
b11 '
b11 ,
b1100 &
b1100 +
1(
#148144
0(
#166662
0;
b11101 8
b11 #
b11 -
b11 R
b11 L
b11 F
b11 @
b0 :
0*
1(
#185180
0(
#203698
0A
b11110 >
b1 ?
b0 @
b111 F
b111 L
b111 R
b111 #
b111 -
1(
#222216
0(
#240734
b1111 #
b1111 -
b1111 R
b1111 L
b0 F
b100000 D
b11 E
b1 C
1(
#259252
0(
#277770
0M
b11101 J
b1 L
b11111 R
b11111 #
b11111 -
1(
#296288
0(
#314806
0S
b11101 P
b111111 #
b111111 -
b10 R
1(
#333324
0(
#351842
1!
b100 #
b100 -
1(
#370360
0(
#388878
0!
1(
#407396
0(
#425914
1(
#444432
0(
#462950
1(
#481468
0(
#499986
1(
#518504
0(
#537022
b11100 3
1*
b100 '
b100 ,
b1111 &
b1111 +
1(
#555540
0(
#574058
b11100 8
0*
1(
#592576
0(
#611094
b11101 >
1(
#629612
0(
#648130
0G
b11111 D
1(
#666648
0(
#685166
1M
b0 L
b100011 J
b111 K
b11 I
1(
#703684
0(
#722202
1S
b1 R
b100011 P
b111 Q
b11 O
1(
#740720
0(
#759238
1!
b11 #
b11 -
b11 "
b11 .
1(
#777756
0(
#796274
0!
1(
